README.md
setup.py
MarkExcel.egg-info/PKG-INFO
MarkExcel.egg-info/SOURCES.txt
MarkExcel.egg-info/dependency_links.txt
MarkExcel.egg-info/requires.txt
MarkExcel.egg-info/top_level.txt
mark_excel/__init__.py
mark_excel/app.py
mark_excel/merge_write.py
mark_excel/normal_write.py
mark_excel/read.py
mark_excel/write.py
test/1、实例化演示.py
test/2、新增sheet的演示.py
test/3、一行插入单列数据（合并列）的演示.py
test/4、一行插入多列数据的演示.py
test/5、读取演示.py
test/6、合并删除多列数据.py
test/__init__.py