Metadata-Version: 1.0
Name: MarkExcel
Version: 1.0.4
Summary: 工具类整理
Home-page: https://gitee.com/medincmedinc/mark_excel
Author: Mark
Author-email: 1782980833@qq.com
License: MIT Licence
Keywords: MarkExcel,mark
Platform: any
